[
  {
    "email": "reed.snyder@test.it",
    "password": "1!qwerty1!",
    "passMatch": "1!qwerty1!"
  },
  {
    "email": "alexandra.winters@test.it",
    "password": "1!qwerty1!",
    "passMatch": "1!qwerty1!"
  },
  {
    "email": "briana.butler@test.it",
    "password": "1!qwerty1!",
    "passMatch": "1!qwerty1!"
  },
  {
    "email": "klein.gillespie@test.it",
    "password": "1!qwerty1!",
    "passMatch": "1!qwerty1!"
  },
  {
    "email": "pierce.hensley@test.it",
    "password": "1!qwerty1!",
    "passMatch": "1!qwerty1!"
  },
  {
    "email": "dolores.bentley@test.it",
    "password": "1!qwerty1!",
    "passMatch": "1!qwerty1!"
  },
  {
    "email": "juarez.mccormick@test.it",
    "password": "1!qwerty1!",
    "passMatch": "1!qwerty1!"
  },
  {
    "email": "williams.mckay@test.it",
    "password": "1!qwerty1!",
    "passMatch": "1!qwerty1!"
  },
  {
    "email": "teresa.moran@test.it",
    "password": "1!qwerty1!",
    "passMatch": "1!qwerty1!"
  },
  {
    "email": "hall.austin@test.it",
    "password": "1!qwerty1!",
    "passMatch": "1!qwerty1!"
  },
  {
    "email": "berta.galloway@test.it",
    "password": "1!qwerty1!",
    "passMatch": "1!qwerty1!"
  },
  {
    "email": "jarvis.mckenzie@test.it",
    "password": "1!qwerty1!",
    "passMatch": "1!qwerty1!"
  },
  {
    "email": "gabrielle.fleming@test.it",
    "password": "1!qwerty1!",
    "passMatch": "1!qwerty1!"
  },
  {
    "email": "roach.branch@test.it",
    "password": "1!qwerty1!",
    "passMatch": "1!qwerty1!"
  },
  {
    "email": "brennan.harmon@test.it",
    "password": "1!qwerty1!",
    "passMatch": "1!qwerty1!"
  },
  {
    "email": "park.hughes@test.it",
    "password": "1!qwerty1!",
    "passMatch": "1!qwerty1!"
  },
  {
    "email": "josephine.colon@test.it",
    "password": "1!qwerty1!",
    "passMatch": "1!qwerty1!"
  },
  {
    "email": "olga.curtis@test.it",
    "password": "1!qwerty1!",
    "passMatch": "1!qwerty1!"
  },
  {
    "email": "adrienne.joyner@test.it",
    "password": "1!qwerty1!",
    "passMatch": "1!qwerty1!"
  },
  {
    "email": "roslyn.melton@test.it",
    "password": "1!qwerty1!",
    "passMatch": "1!qwerty1!"
  },
  {
    "email": "howe.robbins@test.it",
    "password": "1!qwerty1!",
    "passMatch": "1!qwerty1!"
  },
  {
    "email": "billie.calhoun@test.it",
    "password": "1!qwerty1!",
    "passMatch": "1!qwerty1!"
  },
  {
    "email": "holcomb.waller@test.it",
    "password": "1!qwerty1!",
    "passMatch": "1!qwerty1!"
  },
  {
    "email": "hammond.bowen@test.it",
    "password": "1!qwerty1!",
    "passMatch": "1!qwerty1!"
  },
  {
    "email": "hurst.cohen@test.it",
    "password": "1!qwerty1!",
    "passMatch": "1!qwerty1!"
  }
]