[
  {
    "email": "mai.berg@test.it",
    "password": "1!qwerty1!",
    "passMatch": "1!qwerty1!"
  },
  {
    "email": "cooley.bradshaw@test.it",
    "password": "1!qwerty1!",
    "passMatch": "1!qwerty1!"
  },
  {
    "email": "juliet.salazar@test.it",
    "password": "1!qwerty1!",
    "passMatch": "1!qwerty1!"
  },
  {
    "email": "lottie.berger@test.it",
    "password": "1!qwerty1!",
    "passMatch": "1!qwerty1!"
  },
  {
    "email": "neva.hopper@test.it",
    "password": "1!qwerty1!",
    "passMatch": "1!qwerty1!"
  },
  {
    "email": "walters.becker@test.it",
    "password": "1!qwerty1!",
    "passMatch": "1!qwerty1!"
  },
  {
    "email": "helen.robinson@test.it",
    "password": "1!qwerty1!",
    "passMatch": "1!qwerty1!"
  },
  {
    "email": "glenda.mosley@test.it",
    "password": "1!qwerty1!",
    "passMatch": "1!qwerty1!"
  },
  {
    "email": "delgado.alford@test.it",
    "password": "1!qwerty1!",
    "passMatch": "1!qwerty1!"
  },
  {
    "email": "jennings.hodge@test.it",
    "password": "1!qwerty1!",
    "passMatch": "1!qwerty1!"
  },
  {
    "email": "spence.figueroa@test.it",
    "password": "1!qwerty1!",
    "passMatch": "1!qwerty1!"
  },
  {
    "email": "thomas.durham@test.it",
    "password": "1!qwerty1!",
    "passMatch": "1!qwerty1!"
  },
  {
    "email": "simone.silva@test.it",
    "password": "1!qwerty1!",
    "passMatch": "1!qwerty1!"
  },
  {
    "email": "patel.alston@test.it",
    "password": "1!qwerty1!",
    "passMatch": "1!qwerty1!"
  },
  {
    "email": "johnnie.sexton@test.it",
    "password": "1!qwerty1!",
    "passMatch": "1!qwerty1!"
  },
  {
    "email": "henderson.wilkins@test.it",
    "password": "1!qwerty1!",
    "passMatch": "1!qwerty1!"
  },
  {
    "email": "elsa.deleon@test.it",
    "password": "1!qwerty1!",
    "passMatch": "1!qwerty1!"
  },
  {
    "email": "karyn.fitzpatrick@test.it",
    "password": "1!qwerty1!",
    "passMatch": "1!qwerty1!"
  },
  {
    "email": "ola.edwards@test.it",
    "password": "1!qwerty1!",
    "passMatch": "1!qwerty1!"
  },
  {
    "email": "florine.frank@test.it",
    "password": "1!qwerty1!",
    "passMatch": "1!qwerty1!"
  },
  {
    "email": "peterson.landry@test.it",
    "password": "1!qwerty1!",
    "passMatch": "1!qwerty1!"
  },
  {
    "email": "tabatha.mcpherson@test.it",
    "password": "1!qwerty1!",
    "passMatch": "1!qwerty1!"
  },
  {
    "email": "burks.schwartz@test.it",
    "password": "1!qwerty1!",
    "passMatch": "1!qwerty1!"
  },
  {
    "email": "julianne.perry@test.it",
    "password": "1!qwerty1!",
    "passMatch": "1!qwerty1!"
  },
  {
    "email": "edwina.cantu@test.it",
    "password": "1!qwerty1!",
    "passMatch": "1!qwerty1!"
  }
]